beautifulexcel/__init__.py
beautifulexcel/utils.py
beautifulexcel/writer.py
tests/__init__.py
tests/test_cell_ref.py
beautifulexcel-2024.9.8.16.58.dist-info/LICENSE
beautifulexcel-2024.9.8.16.58.dist-info/METADATA
beautifulexcel-2024.9.8.16.58.dist-info/WHEEL
beautifulexcel-2024.9.8.16.58.dist-info/top_level.txt
beautifulexcel-2024.9.8.16.58.dist-info/RECORD
